allma/__init__.py
allma/main.py
allma-0.1.0.dist-info/LICENSE
allma-0.1.0.dist-info/METADATA
allma-0.1.0.dist-info/WHEEL
allma-0.1.0.dist-info/entry_points.txt
allma-0.1.0.dist-info/RECORD
